BucketCache-0.12.1.dist-info/DESCRIPTION.rst
BucketCache-0.12.1.dist-info/METADATA
BucketCache-0.12.1.dist-info/RECORD
BucketCache-0.12.1.dist-info/WHEEL
BucketCache-0.12.1.dist-info/metadata.json
BucketCache-0.12.1.dist-info/top_level.txt
bucketcache/__init__.py
bucketcache/backends.py
bucketcache/buckets.py
bucketcache/config.py
bucketcache/exceptions.py
bucketcache/keymakers.py
bucketcache/log.py
bucketcache/utilities.py
bucketcache/compat/__init__.py
bucketcache/compat/abc.py
bucketcache/compat/contextlib.py
