Metadata-Version: 2.0
Name: BucketCache
Version: 0.12.1
Summary: Versatile persisent file cache.
Home-page: https://github.com/RazerM/bucketcache
Author: Frazer McLean
Author-email: frazer@frazermclean.co.uk
License: MIT
Platform: UNKNOWN
Classifier: Development Status :: 4 - Beta
Classifier: License :: OSI Approved :: MIT License
Classifier: Programming Language :: Python :: 2.7
Classifier: Programming Language :: Python :: 3
Requires-Dist: boltons
Requires-Dist: decorator (>=4.0.2)
Requires-Dist: logbook (>=0.12.5)
Requires-Dist: python-dateutil
Requires-Dist: represent (>=1.5.1)
Requires-Dist: six (>=1.9.0)
Requires-Dist: pathlib; python_version<"3.4"
Provides-Extra: test
Requires-Dist: msgpack-python; extra == 'test'
Requires-Dist: pytest (>=3); extra == 'test'
Requires-Dist: pytest-benchmark; extra == 'test'
Requires-Dist: pytest-cov; extra == 'test'
Requires-Dist: pytest-xdist; extra == 'test'
Provides-Extra: test
Requires-Dist: mock; python_version<"3.3" and extra == 'test'
